boot/__init__.py
boot/api.py
boot/cli.py
boot/facts.py
boot/facts_collectors.py
boot/types.py
boot/utils.py
boot.py-0.16.dist-info/LICENSE.txt
boot.py-0.16.dist-info/METADATA
boot.py-0.16.dist-info/RECORD
boot.py-0.16.dist-info/WHEEL
boot.py-0.16.dist-info/top_level.txt
