Metadata-Version: 2.1
Name: boot.py
Version: 0.16
Summary: Boot.py is an small set of tools to build simple scripts. Python3 only, and really small: 2Kb!
Home-page: https://github.com/mariocesar/boot.py
Author: Mario César Señoranis Ayala
Author-email: mariocesar.c50@gmail.com
License: UNKNOWN
Platform: UNKNOWN
Classifier: Development Status :: 3 - Alpha
Classifier: Intended Audience :: Developers
Classifier: Programming Language :: Python
Classifier: Programming Language :: Python :: 3
Classifier: Programming Language :: Python :: 3.6
Classifier: License :: OSI Approved :: MIT License
Classifier: Topic :: Software Development :: Libraries :: Python Modules
Requires-Python: >=3.6
